{"schema":{"fields":[{"name":"index","type":"integer"},{"name":"name","type":"string"},{"name":"today","type":"number"},{"name":"yesterday","type":"number"},{"name":"past_week","type":"number"},{"name":"28dayMA","type":"number"}],"primaryKey":["index"],"pandas_version":"0.20.0"},"data":[{"index":0,"name":"PriceUSD","today":12.0659857449,"yesterday":12.1359912953,"past_week":12.6297908484,"28dayMA":13.7064250727},{"index":1,"name":"CapMrktCurUSD","today":145392145.7753811479,"yesterday":146184222.1968501806,"past_week":151876839.1805536151,"28dayMA":164357726.0706346035},{"index":2,"name":"tic_price_avg","today":147.8257069316,"yesterday":149.5747495717,"past_week":152.3711220592,"28dayMA":149.625243616},{"index":3,"name":"tic_usd_cost","today":2523882.9646715368,"yesterday":2708334.8853256945,"past_week":2855832.4579711775,"28dayMA":2939474.4621528699},{"index":4,"name":"pow_hashrate_THs_avg","today":434094.2218543047,"yesterday":415764.7491961415,"past_week":433249.7432432433,"28dayMA":426012.0914358387},{"index":5,"name":"TxCnt","today":4652.0,"yesterday":4520.0,"past_week":4307.0,"28dayMA":4371.9642857143},{"index":6,"name":"TxTfrValMeanNtv","today":29.38255692,"yesterday":34.83066049,"past_week":33.73674673,"28dayMA":34.7677371054},{"index":7,"name":"AdrActCnt","today":23131.0,"yesterday":23435.0,"past_week":22760.0,"28dayMA":22442.3214285714}]}