{"schema":{"fields":[{"name":"index","type":"integer"},{"name":"name","type":"string"},{"name":"today","type":"number"},{"name":"yesterday","type":"number"},{"name":"past_week","type":"number"},{"name":"28dayMA","type":"number"}],"primaryKey":["index"],"pandas_version":"0.20.0"},"data":[{"index":0,"name":"PriceUSD","today":11.350314327,"yesterday":12.6297908484,"past_week":13.6990604686,"28dayMA":14.7173364348},{"index":1,"name":"CapMrktCurUSD","today":136537135.1031503677,"yesterday":151876839.1805536151,"past_week":164455154.2083544135,"28dayMA":176174813.6897447407},{"index":2,"name":"tic_price_avg","today":152.2897455609,"yesterday":152.3711220592,"past_week":149.8607094607,"28dayMA":150.6081009415},{"index":3,"name":"tic_usd_cost","today":2297224.983103476,"yesterday":2855832.4579711775,"past_week":3023996.7062936551,"28dayMA":3270131.8560280642},{"index":4,"name":"pow_hashrate_THs_avg","today":428537.1237113402,"yesterday":433249.7432432433,"past_week":426277.6026936027,"28dayMA":425984.4460872405},{"index":5,"name":"TxCnt","today":4419.0,"yesterday":4307.0,"past_week":4401.0,"28dayMA":4365.0714285714},{"index":6,"name":"TxTfrValMeanNtv","today":39.08069898,"yesterday":33.73674673,"past_week":34.07507358,"28dayMA":36.1347922325},{"index":7,"name":"AdrActCnt","today":21743.0,"yesterday":22760.0,"past_week":20820.0,"28dayMA":22839.8928571429}]}