{"schema":{"fields":[{"name":"index","type":"integer"},{"name":"name","type":"string"},{"name":"today","type":"number"},{"name":"yesterday","type":"number"},{"name":"past_week","type":"number"},{"name":"28dayMA","type":"number"}],"primaryKey":["index"],"pandas_version":"0.20.0"},"data":[{"index":0,"name":"200DMA","today":14.5853554864,"yesterday":14.5707483726,"past_week":14.4792320794,"28dayMA":14.4843970644},{"index":1,"name":"Mayer_Multiple","today":1.0819235983,"yesterday":1.0637444876,"past_week":0.9730748917,"28dayMA":0.9052935267},{"index":2,"name":"PriceUSD","today":15.7802402901,"yesterday":15.4995532616,"past_week":14.0893771882,"28dayMA":13.1157642516}]}