{"schema":{"fields":[{"name":"index","type":"integer"},{"name":"name","type":"string"},{"name":"today","type":"number"},{"name":"yesterday","type":"number"},{"name":"past_week","type":"number"},{"name":"28dayMA","type":"number"}],"primaryKey":["index"],"pandas_version":"0.20.0"},"data":[{"index":0,"name":"CapMVRVCur","today":null,"yesterday":0.74098943,"past_week":0.67008914,"28dayMA":null},{"index":1,"name":"Mayer_Multiple","today":0.8470062615,"yesterday":0.8505328148,"past_week":0.776532764,"28dayMA":0.8335646331},{"index":2,"name":"PriceBTC","today":0.0010587045,"yesterday":0.0010788337,"past_week":0.0010568844,"28dayMA":0.0011156432},{"index":3,"name":"MrktGradient","today":-0.0630021741,"yesterday":-0.0699271324,"past_week":-0.0735340287,"28dayMA":-0.1420561626},{"index":4,"name":"UnrealisedPnL_Net","today":null,"yesterday":-0.3495469103,"past_week":-0.4923387642,"28dayMA":null}]}