{"schema":{"fields":[{"name":"index","type":"integer"},{"name":"name","type":"string"},{"name":"today","type":"number"},{"name":"yesterday","type":"number"},{"name":"past_week","type":"number"},{"name":"28dayMA","type":"number"}],"primaryKey":["index"],"pandas_version":"0.20.0"},"data":[{"index":0,"name":"CapMVRVCur","today":1.49114759,"yesterday":1.4755347,"past_week":1.46161741,"28dayMA":1.3477862368},{"index":1,"name":"Mayer_Multiple","today":2.1742121914,"yesterday":2.1361847538,"past_week":2.0641787577,"28dayMA":1.8284997646},{"index":2,"name":"PriceBTC","today":0.0014097686,"yesterday":0.0014780755,"past_week":0.0014602447,"28dayMA":0.0014202549},{"index":3,"name":"MrktGradient","today":0.5570454886,"yesterday":0.528796789,"past_week":0.4424305788,"28dayMA":0.406057849},{"index":4,"name":"UnrealisedPnL_Net","today":0.3293755709,"yesterday":0.3222795764,"past_week":0.3158264304,"28dayMA":0.253760601}]}